powerline_pws/__init__.py
powerline_pws/segments.py
powerline_pws-1.1.1.dist-info/licenses/LICENSE
powerline_pws-1.1.1.dist-info/METADATA
powerline_pws-1.1.1.dist-info/WHEEL
powerline_pws-1.1.1.dist-info/top_level.txt
powerline_pws-1.1.1.dist-info/RECORD
