Metadata-Version: 2.4
Name: powerline-pws
Version: 1.1.1
Summary: A Powerline segment for showing the PWS station data
Author-email: Bram Oosterlynck <bram.oosterlynck@gmail.com>
License:                     GNU GENERAL PUBLIC LICENSE
Project-URL: Homepage, https://github.com/boosterl/powerline-pws
Project-URL: Repository, https://github.com/boosterl/powerline-pws.git
Project-URL: Issues, https://github.com/boosterl/powerline-pws
Keywords: powerline weather-station weewx pws personal-weather-station powerline-segment
Classifier: License :: OSI Approved :: GNU General Public License v3 (GPLv3)
Classifier: Intended Audience :: Developers
Classifier: Programming Language :: Python :: 3
Classifier: Programming Language :: Python :: 3.8
Classifier: Programming Language :: Python :: 3.9
Classifier: Programming Language :: Python :: 3.10
Classifier: Programming Language :: Python :: 3.11
Classifier: Programming Language :: Python :: 3.12
License-File: LICENSE
Dynamic: license-file
